flaskmason/__init__.py
flaskmason/generator.py
flaskmason-0.1.4.dist-info/METADATA
flaskmason-0.1.4.dist-info/WHEEL
flaskmason-0.1.4.dist-info/entry_points.txt
flaskmason-0.1.4.dist-info/top_level.txt
flaskmason-0.1.4.dist-info/RECORD
