Metadata-Version: 2.1
Name: flaskmason
Version: 0.1.4
Summary: A CLI tool to generate a Django-like structure for Flask projects
Home-page: https://github.com/Akash-nath29/flaskgen
Author: Akash Nath
Author-email: devakash2905@gmail.com
Classifier: Programming Language :: Python :: 3
Classifier: License :: OSI Approved :: MIT License
Classifier: Operating System :: OS Independent
Requires-Python: >=3.6
Requires-Dist: Flask >=2.0
Requires-Dist: Flask-SQLAlchemy >=2.5
Requires-Dist: Flask-WTF >=0.15
